{
  "run_id": "e52b537c",
  "timestamp": "2026-05-04T06:53:50.836667+00:00",
  "total_runtime_sec": 8.936041332999594,
  "fit_count": 7,
  "n_candidates": 7,
  "splits_summary": "train: 2015-01-01 -> 2019-04-10 (1561 rows)\nval:   2019-04-11 -> 2019-10-07 (180 rows)\ntest:  2019-10-08 -> 2020-10-06 (365 rows)  [LOCKED]",
  "best_name": "mlp__cal_temp_apptemp_lag1-7_roll7__hls128x64_actrelu_solveradam_alpha0.001_lrinit0.01_iter500",
  "best_metric": 8879955.29711122,
  "baseline_name": "seasonal_naive_364",
  "baseline_metric": 60410778.91466296,
  "improvement_vs_baseline": 51530823.61755174,
  "prev_champion_name": "mlp__cal_temp_apptemp_lag1-7_roll7__hls128x64_actrelu_solveradam_alpha0.001_lrinit0.01_iter500",
  "prev_champion_metric": 8879955.29711122,
  "new_champion": false,
  "improvement_vs_champion": 0.0,
  "env": {
    "python": "3.10.5",
    "platform": "macOS-26.3.1-arm64-arm-64bit",
    "promote_on": "val",
    "evaluate_on_test": "True"
  },
  "results": [
    {
      "name": "seasonal_naive_7",
      "feature_config": {
        "use_calendar": false,
        "use_temp": false,
        "use_apparent_temp": false,
        "use_rrp": false,
        "demand_lags": [],
        "rolling_windows": []
      },
      "is_baseline": true,
      "metrics": {
        "mse_demand": 141138183.6274827,
        "rmse_demand": 11880.159242513659,
        "mae_demand": 9762.271280820696
      },
      "runtime_sec": 0.010553875006735325,
      "n_train": 1561,
      "n_val": 180,
      "n_features": 0,
      "error": null,
      "test_metrics": {
        "mse_demand": 207834241.32481366,
        "rmse_demand": 14416.45730839632,
        "mae_demand": 12113.128072003377
      },
      "n_test": 365
    },
    {
      "name": "seasonal_naive_364",
      "feature_config": {
        "use_calendar": false,
        "use_temp": false,
        "use_apparent_temp": false,
        "use_rrp": false,
        "demand_lags": [],
        "rolling_windows": []
      },
      "is_baseline": true,
      "metrics": {
        "mse_demand": 60410778.91466296,
        "rmse_demand": 7772.437128382768,
        "mae_demand": 6270.753833333328
      },
      "runtime_sec": 0.007421374990371987,
      "n_train": 1561,
      "n_val": 180,
      "n_features": 0,
      "error": null,
      "test_metrics": {
        "mse_demand": 224849543.5511672,
        "rmse_demand": 14994.983946345765,
        "mae_demand": 11030.623232639775
      },
      "n_test": 365
    },
    {
      "name": "mlp__cal_temp_apptemp_lag1-7_roll7__hls128x64_actrelu_solveradam_alpha0.001_lrinit0.01_iter500",
      "feature_config": {
        "use_calendar": true,
        "use_temp": true,
        "use_apparent_temp": true,
        "use_rrp": false,
        "demand_lags": [
          1,
          7
        ],
        "rolling_windows": [
          7
        ]
      },
      "is_baseline": false,
      "metrics": {
        "mse_demand": 8879955.29711122,
        "rmse_demand": 2979.9253844872055,
        "mae_demand": 2320.079796091271
      },
      "runtime_sec": 3.934739125004853,
      "n_train": 1550,
      "n_val": 180,
      "n_features": 24,
      "error": null,
      "test_metrics": {
        "mse_demand": 18937353.75409846,
        "rmse_demand": 4351.706993134816,
        "mae_demand": 3468.1180754548304
      },
      "n_test": 365
    },
    {
      "name": "gbm__cal_temp_lag1-7_roll7__n300_depth3_lr0.05_sub1.0_losshuber",
      "feature_config": {
        "use_calendar": true,
        "use_temp": true,
        "use_apparent_temp": false,
        "use_rrp": false,
        "demand_lags": [
          1,
          7
        ],
        "rolling_windows": [
          7
        ]
      },
      "is_baseline": false,
      "metrics": {
        "mse_demand": 11807564.053878149,
        "rmse_demand": 3436.21362168858,
        "mae_demand": 2563.243919234777
      },
      "runtime_sec": 1.9566110409941757,
      "n_train": 1550,
      "n_val": 180,
      "n_features": 21,
      "error": null,
      "test_metrics": {
        "mse_demand": 24283729.72841481,
        "rmse_demand": 4927.852445885003,
        "mae_demand": 3888.3313633523785
      },
      "n_test": 365
    },
    {
      "name": "gbm__cal_temp_lag1-7_roll7__n300_depth5_lr0.05_sub1.0",
      "feature_config": {
        "use_calendar": true,
        "use_temp": true,
        "use_apparent_temp": false,
        "use_rrp": false,
        "demand_lags": [
          1,
          7
        ],
        "rolling_windows": [
          7
        ]
      },
      "is_baseline": false,
      "metrics": {
        "mse_demand": 11027505.093745252,
        "rmse_demand": 3320.768750416875,
        "mae_demand": 2511.564709044716
      },
      "runtime_sec": 2.1164389999903506,
      "n_train": 1550,
      "n_val": 180,
      "n_features": 21,
      "error": null,
      "test_metrics": {
        "mse_demand": 22504541.163839858,
        "rmse_demand": 4743.895146800765,
        "mae_demand": 3737.3756895249453
      },
      "n_test": 365
    },
    {
      "name": "numpy_ols__full__alpha0.0",
      "feature_config": {
        "use_calendar": true,
        "use_temp": true,
        "use_apparent_temp": true,
        "use_rrp": true,
        "demand_lags": [
          1,
          7
        ],
        "rolling_windows": [
          7
        ]
      },
      "is_baseline": false,
      "metrics": {
        "mse_demand": 40051427.76577628,
        "rmse_demand": 6328.6197362281355,
        "mae_demand": 5015.745511979241
      },
      "runtime_sec": 0.005551291003939696,
      "n_train": 1550,
      "n_val": 180,
      "n_features": 25,
      "error": null,
      "test_metrics": {
        "mse_demand": 48317414.707715385,
        "rmse_demand": 6951.072917738339,
        "mae_demand": 5534.229307735374
      },
      "n_test": 365
    },
    {
      "name": "gbm__cal_temp_apptemp_lag1-7__n500_depth3_lr0.05_sub0.8_patience10_valf0.15",
      "feature_config": {
        "use_calendar": true,
        "use_temp": true,
        "use_apparent_temp": true,
        "use_rrp": false,
        "demand_lags": [
          1,
          7
        ],
        "rolling_windows": []
      },
      "is_baseline": false,
      "metrics": {
        "mse_demand": 12310940.464658642,
        "rmse_demand": 3508.6949802823615,
        "mae_demand": 2705.7752386445813
      },
      "runtime_sec": 0.903904999999213,
      "n_train": 1550,
      "n_val": 180,
      "n_features": 23,
      "error": null,
      "test_metrics": {
        "mse_demand": 22406501.54092035,
        "rmse_demand": 4733.55062726917,
        "mae_demand": 3761.230790935794
      },
      "n_test": 365
    }
  ]
}